base_locale/__init__.py
base_locale/admin.py
base_locale/apps.py
base_locale/exceptions.py
base_locale/models.py
base_locale/tests.py
base_locale/urls.py
base_locale/utils.py
base_locale/views.py
base_locale/locale/de/LC_MESSAGES/django.mo
base_locale/locale/en/LC_MESSAGES/django.mo
base_locale/locale/ru/LC_MESSAGES/django.mo
base_locale/locale/uk/LC_MESSAGES/django.mo
base_locale/migrations/0001_initial.py
base_locale/migrations/__init__.py
base_locale/templatetags/__init__.py
base_locale/templatetags/base_locale_extras.py
django_base_locale-4.2.0.dist-info/LICENSE.md
django_base_locale-4.2.0.dist-info/METADATA
django_base_locale-4.2.0.dist-info/WHEEL
django_base_locale-4.2.0.dist-info/top_level.txt
django_base_locale-4.2.0.dist-info/RECORD
