Metadata-Version: 2.1
Name: django-base-locale
Version: 4.2.0
Summary: Simple way to create multi language Django app.
Home-page: https://github.com/Maksych/django_base_locale
Author: Maksym Sichkaruk
Author-email: maxim.18.08.1997@gmail.com
License: MIT
Platform: UNKNOWN
